transmep/__init__.py
transmep/__main__.py
transmep/cli.py
transmep/criterion_optimization.py
transmep/data.py
transmep/foundation_model.py
transmep/model.py
transmep/optimize.py
transmep/questionary_validation.py
transmep/reports.py
transmep/stats.py
transmep-0.1.0.dist-info/LICENSE
transmep-0.1.0.dist-info/METADATA
transmep-0.1.0.dist-info/WHEEL
transmep-0.1.0.dist-info/entry_points.txt
transmep-0.1.0.dist-info/RECORD
