Metadata-Version: 2.1
Name: transmep
Version: 0.1.0
Summary: Transfer learning for Mutation Effect Prediction
License: MIT
Author: Tilman Hoffbauer
Author-email: tilman.hoffbauer@rwth-aachen.de
Requires-Python: >=3.8,<3.11
Classifier: License :: OSI Approved :: MIT License
Classifier: Programming Language :: Python :: 3
Classifier: Programming Language :: Python :: 3.8
Classifier: Programming Language :: Python :: 3.9
Classifier: Programming Language :: Python :: 3.10
Requires-Dist: aiohttp (>=3.8,<4.0)
Requires-Dist: arch (>=5.2.0,<6.0.0)
Requires-Dist: captum (>=0.5,<0.6)
Requires-Dist: click (>=8.1,<9.0)
Requires-Dist: deap (>=1.3.3,<2.0.0)
Requires-Dist: fair-esm (>=1.0.2,<2.0.0)
Requires-Dist: fsspec (>=2022.3,<2023.0)
Requires-Dist: kaleido (==0.2.1)
Requires-Dist: numpy (>=1.21,<2.0)
Requires-Dist: plotly (>=5.7,<6.0)
Requires-Dist: questionary (>=1.10,<2.0)
Requires-Dist: requests (>=2.27,<3.0)
Requires-Dist: scikit-learn (>=1.0,<2.0)
Requires-Dist: torch (==1.12.1)
Requires-Dist: tqdm (>=4.64,<5.0)
